{
    "name": "EMF_Gamepad_Local_Dev",
    "description": "",
    "dependencies": {
        "core": "*",
        "radio": "*",
        "microphone": "*",
        "EMF_Gamepad": "github:dmacmakes/emakefun-microbit-gamepad-makecode-en#main"
    },
    "files": [
        "main.blocks",
        "main.ts",
        "README.md"
    ],
    "testFiles": [
        "test.ts"
    ],
    "targetVersions": {
        "target": "6.0.15",
        "targetId": "microbit"
    },
    "supportedTargets": [
        "microbit"
    ],
    "preferredEditor": "blocksprj"
}
